rpdk/typescript/__init__.py
rpdk/typescript/codegen.py
rpdk/typescript/parser.py
rpdk/typescript/resolver.py
rpdk/typescript/utils.py
rpdk/typescript/data/.npmrc
rpdk/typescript/data/__init__.py
rpdk/typescript/data/create.json
rpdk/typescript/data/tsconfig.json
rpdk/typescript/data/typescript.gitignore
rpdk/typescript/templates/README.md
rpdk/typescript/templates/handlers.ts
rpdk/typescript/templates/models.ts
rpdk/typescript/templates/package.json
cloudformation_cli_typescript_plugin-1.0.2.dist-info/LICENSE
cloudformation_cli_typescript_plugin-1.0.2.dist-info/METADATA
cloudformation_cli_typescript_plugin-1.0.2.dist-info/WHEEL
cloudformation_cli_typescript_plugin-1.0.2.dist-info/entry_points.txt
cloudformation_cli_typescript_plugin-1.0.2.dist-info/top_level.txt
cloudformation_cli_typescript_plugin-1.0.2.dist-info/zip-safe
cloudformation_cli_typescript_plugin-1.0.2.dist-info/RECORD
