Metadata-Version: 2.1
Name: cloudformation-cli-typescript-plugin
Version: 1.0.2
Summary: Typescript language support for the CloudFormation CLI
Home-page: https://github.com/aws-cloudformation/cloudformation-cli-typescript-plugin
Author: Amazon Web Services
Author-email: aws-cloudformation-developers@amazon.com
License: Apache License 2.0
Keywords: Amazon Web Services AWS CloudFormation
Classifier: Development Status :: 5 - Production/Stable
Classifier: Environment :: Console
Classifier: Intended Audience :: Developers
Classifier: License :: OSI Approved :: Apache Software License
Classifier: Natural Language :: English
Classifier: Topic :: Software Development :: Build Tools
Classifier: Topic :: Software Development :: Code Generators
Classifier: Operating System :: OS Independent
Classifier: Programming Language :: Python :: 3 :: Only
Classifier: Programming Language :: Python :: 3.6
Classifier: Programming Language :: Python :: 3.7
Classifier: Programming Language :: Python :: 3.8
Requires-Python: >=3.6
License-File: LICENSE
Requires-Dist: cloudformation-cli (>=0.1.14)
Requires-Dist: zipfile38 (<0.2,>=0.0.3)
